chinesebert/__init__.py
chinesebert/classifier.py
chinesebert/configuration_chinesebert.py
chinesebert/fusion_embedding.py
chinesebert/glyph_embedding.py
chinesebert/modeling_chinesebert.py
chinesebert/pinyin_embedding.py
chinesebert/tokenization_chinesebert_fast.py
chinesebert/transformers_patch_utils.py
chinesebert-0.2.1.dist-info/LICENSE
chinesebert-0.2.1.dist-info/METADATA
chinesebert-0.2.1.dist-info/WHEEL
chinesebert-0.2.1.dist-info/top_level.txt
chinesebert-0.2.1.dist-info/RECORD
