Metadata-Version: 2.1
Name: chinesebert
Version: 0.2.1
Summary: ChineseBert_pytorch
Home-page: https://github.com/JunnYu/ChineseBert_pytorch
Author: Jun Yu
Author-email: 573009727@qq.com
License: MIT
Keywords: ChineseBert,pytorch
Platform: UNKNOWN
Requires-Dist: transformers (>=4.14.1)
Requires-Dist: pypinyin (==0.38.1)
